ir_evaluation/__init__.py
ir_evaluation/metrics.py
ir_evaluation/py.typed
ir_evaluation-1.1.0.dist-info/METADATA
ir_evaluation-1.1.0.dist-info/WHEEL
ir_evaluation-1.1.0.dist-info/licenses/LICENSE
ir_evaluation-1.1.0.dist-info/RECORD
