Metadata-Version: 2.4
Name: ir_evaluation
Version: 1.1.0
Summary: Information retrieval evaluation metrics in pure python with zero dependencies
Project-URL: Homepage, https://github.com/plurch/ir_evaluation
Project-URL: Issues, https://github.com/plurch/ir_evaluation/issues
Author-email: Patrick Lurch <plurch@users.noreply.github.com>
License-File: LICENSE
Keywords: Data science,Evaluation metrics,Information retrieval,Recommender systems
Classifier: Development Status :: 5 - Production/Stable
Classifier: Intended Audience :: Developers
Classifier: Intended Audience :: Science/Research
Classifier: License :: OSI Approved :: MIT License
Classifier: Natural Language :: English
Classifier: Operating System :: OS Independent
Classifier: Programming Language :: Python :: 3
Classifier: Topic :: Scientific/Engineering :: Information Analysis
Classifier: Topic :: Software Development :: Libraries :: Python Modules
Requires-Python: >=3.11
